{
    "data": [
        {
            "diary_no": "264-2022",
            "Judgement_type": "J",
            "case_no": "C.A. No.-004177-004177 - 2024",
            "pet": "SK. GOLAM LALCHAND",
            "res": "NANDU LAL SHAW @ NAND LAL KESHRI @ NANDU LAL BAYES",
            "pet_adv": "RAUF RAHIM",
            "res_adv": null,
            "bench": "HON&#39;BLE MR. JUSTICE SUDHANSHU DHULIA, HON&#39;BLE MR. JUSTICE PANKAJ MITHAL",
            "judgement_by": "HON&#39;BLE MR. JUSTICE PANKAJ MITHAL",
            "judgment_dates": "10-09-2024",
            "temp_link": "supremecourt/2022/264/264_2022_12_1501_55549_Judgement_10-Sep-2024.pdf (English)"
        },
        {
            "diary_no": "1551-2021",
            "Judgement_type": "J",
            "case_no": "C.A. No.-000258-000259 - 2021",
            "pet": "PUNE MUNICIPAL CORPORATION",
            "res": "SUS ROAD BANER VIKAS MANCH",
            "pet_adv": "NISHTHA KUMAR",
            "res_adv": null,
            "bench": "HON&#39;BLE MR. JUSTICE B.R. GAVAI, HON&#39;BLE MR. JUSTICE PRASHANT KUMAR MISHRA, HON&#39;BLE MR. JUSTICE K.V. VISWANATHAN",
            "judgement_by": "HON&#39;BLE MR. JUSTICE B.R. GAVAI",
            "judgment_dates": "12-09-2024",
            "temp_link": "supremecourt/2021/1551/1551_2021_3_1501_55507_Judgement_12-Sep-2024.pdf (English)"
        },
        {
            "diary_no": "2840-2021",
            "Judgement_type": "J",
            "case_no": "Crl.A. No.-003863-003863 - 2024",
            "pet": "CENTRAL BUREAU OF INVESTIGATION",
            "res": "DILIP MULANI",
            "pet_adv": "MUKESH KUMAR MARORIA",
            "res_adv": null,
            "bench": "HON&#39;BLE MR. JUSTICE ABHAY S. OKA, HON&#39;BLE MR. JUSTICE PANKAJ MITHAL",
            "judgement_by": "HON&#39;BLE MR. JUSTICE ABHAY S. OKA",
            "judgment_dates": "20-09-2024",
            "temp_link": "supremecourt/2021/2840/2840_2021_6_1501_55871_Judgement_20-Sep-2024.pdf (English)"
        },
        {
            "diary_no": "4287-2012",
            "Judgement_type": "J",
            "case_no": "C.A. No.-009482-009482 - 2013",
            "pet": "KAMAL KISHOR SEHGAL(D) THR.LRS.",
            "res": "MURTI DEVI (DEAD) THR. LRS.",
            "pet_adv": "KRISHAN KUMAR",
            "res_adv": "PRAMOD DAYAL",
            "bench": "HON&#39;BLE MR. JUSTICE ABHAY S. OKA, HON&#39;BLE MR. JUSTICE PANKAJ MITHAL, HON&#39;BLE MR. JUSTICE AHSANUDDIN AMANULLAH",
            "judgement_by": "HON&#39;BLE MR. JUSTICE PANKAJ MITHAL",
            "judgment_dates": "19-09-2024",
            "temp_link": "supremecourt/2012/4287/4287_2012_6_1501_55857_Judgement_19-Sep-2024.pdf (English)"
        },
        {
            "diary_no": "4586-2016",
            "Judgement_type": "J",
            "case_no": "C.A. No.-001689-001689 - 2016",
            "pet": "SECRETARY, PUBLIC WORKS DEPARTMENT .",
            "res": "TUKARAM PANDURANG SARAF .",
            "pet_adv": "AADITYA ANIRUDDHA PANDE",
            "res_adv": null,
            "bench": "HON&#39;BLE MR. JUSTICE PAMIDIGHANTAM SRI NARASIMHA, HON&#39;BLE MR. JUSTICE SANDEEP MEHTA",
            "judgement_by": "HON&#39;BLE MR. JUSTICE SANDEEP MEHTA",
            "judgment_dates": "19-09-2024",
            "temp_link": "supremecourt/2016/4586/4586_2016_14_1502_55860_Judgement_19-Sep-2024.pdf (English)"
        },
        {
            "diary_no": "5562-2019",
            "Judgement_type": "J",
            "case_no": "C.A. No.-009702-009702 - 2024",
            "pet": "KUKREJA CONSTRUCTION COMPANY",
            "res": "THE STATE OF MAHARASHTRA",
            "pet_adv": "E. C. AGRAWALA",
            "res_adv": null,
            "bench": "HON&#39;BLE MRS. JUSTICE B.V. NAGARATHNA, HON&#39;BLE MR. JUSTICE NONGMEIKAPAM KOTISWAR SINGH",
            "judgement_by": "HON&#39;BLE MRS. JUSTICE B.V. NAGARATHNA",
            "judgment_dates": "13-09-2024",
            "temp_link": "supremecourt/2019/5562/5562_2019_9_1501_55643_Judgement_13-Sep-2024.pdf (English)"
        },
        {
            "diary_no": "5895-2018",
            "Judgement_type": "J",
            "case_no": "C.A. No.-010192-010192 - 2024",
            "pet": "VAIBHAV JAIN",
            "res": "HINDUSTAN MOTORS PVT. LTD.",
            "pet_adv": "ARUP BANERJEE",
            "res_adv": null,
            "bench": "HON&#39;BLE MR. JUSTICE MANOJ MISRA, HON&#39;BLE MR. JUSTICE RAJESH BINDAL",
            "judgement_by": "HON&#39;BLE MR. JUSTICE MANOJ MISRA",
            "judgment_dates": "03-09-2024",
            "temp_link": "supremecourt/2018/5895/5895_2018_8_1502_55423_Judgement_03-Sep-2024.pdf (English)"
        },
        {
            "diary_no": "6241-2019",
            "Judgement_type": "J",
            "case_no": "Crl.A. No.-000449-000450 - 2019",
            "pet": "RABBU @ SARVESH",
            "res": "THE STATE OF MADHYA PRADESH",
            "pet_adv": "ZEHRA KHAN",
            "res_adv": null,
            "bench": "HON&#39;BLE MR. JUSTICE B.R. GAVAI, HON&#39;BLE MR. JUSTICE PRASHANT KUMAR MISHRA, HON&#39;BLE MR. JUSTICE K.V. VISWANATHAN",
            "judgement_by": "HON&#39;BLE MR. JUSTICE B.R. GAVAI",
            "judgment_dates": "12-09-2024",
            "temp_link": "supremecourt/2019/6241/6241_2019_3_101_55507_Judgement_12-Sep-2024.pdf (English)"
        },
        {
            "diary_no": "6444-2012",
            "Judgement_type": "J",
            "case_no": "C.A. No.-003190-003190 - 2014",
            "pet": "BEENA",
            "res": "CHARAN DASS (D) THR LRS",
            "pet_adv": "PUNEET TANEJA",
            "res_adv": "RAJESH SRIVASTAVA",
            "bench": "HON&#39;BLE MR. JUSTICE PANKAJ MITHAL, HON&#39;BLE MR. JUSTICE R. MAHADEVAN",
            "judgement_by": "HON&#39;BLE MR. JUSTICE M.M. SUNDRESH",
            "judgment_dates": "11-09-2024",
            "temp_link": "supremecourt/2012/6444/6444_2012_12_1501_55516_Judgement_11-Sep-2024.pdf (English)"
        },
        {
            "diary_no": "7124-2018",
            "Judgement_type": "J",
            "case_no": "C.A. No.-008374-008374 - 2024",
            "pet": "SIDDARAJA MANICKA PRABHU TEMPLE",
            "res": "THE IDOL OF ARULMIGHU KAMAKALA KAMESHWARAR TEMPLE",
            "pet_adv": "AKSHAY GIRISH RINGE",
            "res_adv": null,
            "bench": "HON&#39;BLE MR. JUSTICE ABHAY S. OKA, HON&#39;BLE MR. JUSTICE AUGUSTINE GEORGE MASIH",
            "judgement_by": "HON&#39;BLE MR. JUSTICE AUGUSTINE GEORGE MASIH",
            "judgment_dates": "13-09-2024",
            "temp_link": "supremecourt/2018/7124/7124_2018_6_1501_55640_Judgement_13-Sep-2024.pdf (English)"
        },
        {
            "diary_no": "8253-2022",
            "Judgement_type": "J",
            "case_no": "Crl.A. No.-004058-004058 - 2024",
            "pet": "K. VADIVEL",
            "res": "K. SHANTHI",
            "pet_adv": "VINODH KANNA B.",
            "res_adv": null,
            "bench": "HON&#39;BLE MR. JUSTICE B.R. GAVAI, HON&#39;BLE MR. JUSTICE K.V. VISWANATHAN",
            "judgement_by": "HON&#39;BLE MR. JUSTICE K.V. VISWANATHAN",
            "judgment_dates": "30-09-2024",
            "temp_link": "supremecourt/2022/8253/8253_2022_3_1501_56161_Judgement_30-Sep-2024.pdf (English)"
        },
        {
            "diary_no": "8562-2024",
            "Judgement_type": "J",
            "case_no": "Crl.A. No.-002161-002162 - 2024",
            "pet": "JUST RIGHTS FOR CHILDREN ALLIANCE",
            "res": "S. HARISH",
            "pet_adv": "SAKSHAM MAHESHWARI ",
            "res_adv": null,
            "bench": "HON&#39;BLE THE CHIEF JUSTICE, HON&#39;BLE MR. JUSTICE J.B. PARDIWALA",
            "judgement_by": "HON&#39;BLE MR. JUSTICE J.B. PARDIWALA",
            "judgment_dates": "23-09-2024",
            "temp_link": "supremecourt/2024/8562/8562_2024_1_1501_56073_Judgement_23-Sep-2024.pdf (English)"
        },
        {
            "diary_no": "8588-2022",
            "Judgement_type": "J",
            "case_no": "Crl.A. No.-002221-002222 - 2023",
            "pet": "ABHISHEK BANERJEE",
            "res": "DIRECTORATE OF ENFORCEMENT",
            "pet_adv": "UDAYADITYA BANERJEE",
            "res_adv": null,
            "bench": "HON&#39;BLE MS. JUSTICE BELA M. TRIVEDI, HON&#39;BLE MR. JUSTICE SATISH CHANDRA SHARMA",
            "judgement_by": "HON&#39;BLE MS. JUSTICE BELA M. TRIVEDI",
            "judgment_dates": "09-09-2024",
            "temp_link": "supremecourt/2022/8588/8588_2022_13_1501_55472_Judgement_09-Sep-2024.pdf (English)"
        },
        {
            "diary_no": "8870-2024",
            "Judgement_type": "J",
            "case_no": "Crl.A. No.-002764-002764 - 2024",
            "pet": "RAGHUVEER SHARAN",
            "res": "DISTRICT SAHAKARI KRISHI GRAMIN VIKAS BANK",
            "pet_adv": "KAJAL SHARMA",
            "res_adv": null,
            "bench": "HON&#39;BLE MR. JUSTICE DIPANKAR DATTA, HON&#39;BLE MR. JUSTICE PRASHANT KUMAR MISHRA",
            "judgement_by": "HON&#39;BLE MR. JUSTICE PRASHANT KUMAR MISHRA",
            "judgment_dates": "10-09-2024",
            "temp_link": "supremecourt/2024/8870/8870_2024_16_1501_55554_Judgement_10-Sep-2024.pdf (English)"
        },
        {
            "diary_no": "9236-2021",
            "Judgement_type": "J",
            "case_no": "C.A. No.-010804-010804 - 2024",
            "pet": "SHYAMSUNDAR RADHESHYAM AGRAWAL",
            "res": "PUSHPABAI NILKANTH PATIL",
            "pet_adv": "C. GEORGE THOMAS",
            "res_adv": null,
            "bench": "HON&#39;BLE MR. JUSTICE PANKAJ MITHAL, HON&#39;BLE MR. JUSTICE R. MAHADEVAN",
            "judgement_by": "HON&#39;BLE MR. JUSTICE R. MAHADEVAN",
            "judgment_dates": "24-09-2024",
            "temp_link": "supremecourt/2021/9236/9236_2021_17_1501_56034_Judgement_24-Sep-2024.pdf (English)"
        },
        {
            "diary_no": "9406-2022",
            "Judgement_type": "J",
            "case_no": "C.A. No.-010039-010040 - 2024",
            "pet": "SEETHARAMA SHETTY",
            "res": "MONAPPA SHETTY",
            "pet_adv": "ANIRUDH SANGANERIA",
            "res_adv": null,
            "bench": "HON&#39;BLE MR. JUSTICE HRISHIKESH ROY, HON&#39;BLE MR. JUSTICE S.V.N. BHATTI",
            "judgement_by": "HON&#39;BLE MR. JUSTICE S.V.N. BHATTI",
            "judgment_dates": "02-09-2024",
            "temp_link": "supremecourt/2022/9406/9406_2022_5_1502_55218_Judgement_02-Sep-2024.pdf (English)"
        },
        {
            "diary_no": "9761-2017",
            "Judgement_type": "J",
            "case_no": "C.A. No.-010193-010193 - 2024",
            "pet": "ISHWAR (SINCE DECEASED)  THR. LRS",
            "res": "BHIM SINGH",
            "pet_adv": "B. S. BANTHIA",
            "res_adv": null,
            "bench": "HON&#39;BLE MR. JUSTICE MANOJ MISRA, HON&#39;BLE MR. JUSTICE RAJESH BINDAL",
            "judgement_by": "HON&#39;BLE MR. JUSTICE MANOJ MISRA",
            "judgment_dates": "03-09-2024",
            "temp_link": "supremecourt/2017/9761/9761_2017_8_1501_55423_Judgement_03-Sep-2024.pdf (English)"
        },
        {
            "diary_no": "10557-2021",
            "Judgement_type": "J",
            "case_no": "C.A. No.-012135-012135 - 2024",
            "pet": "BAJAJ ALLIANZ LIFE INSURANCE COMPANY LTD.",
            "res": "SAROJ KUMAR  PANDA",
            "pet_adv": "PRAGYA BAGHEL",
            "res_adv": null,
            "bench": "HON&#39;BLE MR. JUSTICE J.K. MAHESHWARI, HON&#39;BLE MR. JUSTICE RAJESH BINDAL",
            "judgement_by": "HON&#39;BLE MR. JUSTICE J.K. MAHESHWARI",
            "judgment_dates": "23-09-2024",
            "temp_link": "supremecourt/2021/10557/10557_2021_8_37_55930_Judgement_23-Sep-2024.pdf (English)"
        },
        {
            "diary_no": "10562-2012",
            "Judgement_type": "J",
            "case_no": "C.A. No.-008617-008617 - 2013",
            "pet": "V.VINCENT VELANKANNI",
            "res": "UNION OF INDIA .",
            "pet_adv": null,
            "res_adv": null,
            "bench": "HON&#39;BLE MR. JUSTICE PAMIDIGHANTAM SRI NARASIMHA, HON&#39;BLE MR. JUSTICE SANDEEP MEHTA",
            "judgement_by": "HON&#39;BLE MR. JUSTICE PAMIDIGHANTAM SRI NARASIMHA",
            "judgment_dates": "30-09-2024",
            "temp_link": "supremecourt/2012/10562/10562_2012_14_1501_56170_Judgement_30-Sep-2024.pdf (English)"
        },
        {
            "diary_no": "12721-2024",
            "Judgement_type": "J",
            "case_no": "Crl.A. No.-004011-004011 - 2024",
            "pet": "V. SENTHIL BALAJI",
            "res": "THE DEPUTY DIRECTOR",
            "pet_adv": "RAM SANKAR & CO",
            "res_adv": null,
            "bench": "HON&#39;BLE MR. JUSTICE ABHAY S. OKA, HON&#39;BLE MR. JUSTICE AUGUSTINE GEORGE MASIH",
            "judgement_by": "HON&#39;BLE MR. JUSTICE ABHAY S. OKA",
            "judgment_dates": "26-09-2024",
            "temp_link": "supremecourt/2024/12721/12721_2024_6_1501_56009_Judgement_26-Sep-2024.pdf (English)"
        },
        {
            "diary_no": "13152-2024",
            "Judgement_type": "J",
            "case_no": "Crl.A. No.-003083-003083 - 2024",
            "pet": "JASEELA SHAJI",
            "res": "THE UNION OF INDIA",
            "pet_adv": "K. RAJEEV",
            "res_adv": null,
            "bench": "HON&#39;BLE MR. JUSTICE B.R. GAVAI, HON&#39;BLE MR. JUSTICE PRASHANT KUMAR MISHRA, HON&#39;BLE MR. JUSTICE K.V. VISWANATHAN",
            "judgement_by": "HON&#39;BLE MR. JUSTICE B.R. GAVAI",
            "judgment_dates": "12-09-2024",
            "temp_link": "supremecourt/2024/13152/13152_2024_3_1502_55507_Judgement_12-Sep-2024.pdf (English)"
        },
        {
            "diary_no": "13430-2024",
            "Judgement_type": "J",
            "case_no": "ARBIT.PETITON No.-000019 - 2024",
            "pet": "AJAY MADHUSUDAN PATEL",
            "res": "JYOTRINDRA S. PATEL",
            "pet_adv": "SHAMIK SHIRISHBHAI SANJANWALA",
            "res_adv": null,
            "bench": "HON&#39;BLE THE CHIEF JUSTICE, HON&#39;BLE MR. JUSTICE J.B. PARDIWALA, HON&#39;BLE MR. JUSTICE MANOJ MISRA",
            "judgement_by": "HON&#39;BLE MR. JUSTICE J.B. PARDIWALA",
            "judgment_dates": "20-09-2024",
            "temp_link": "supremecourt/2024/13430/13430_2024_1_1502_55866_Judgement_20-Sep-2024.pdf (English)"
        },
        {
            "diary_no": "13533-2015",
            "Judgement_type": "J",
            "case_no": "Crl.A. No.-001031-001031 - 2015",
            "pet": "VIJAY SINGH @ VIJAY KR. SHARMA",
            "res": "THE STATE OF BIHAR",
            "pet_adv": "AJAY KUMAR SINGH",
            "res_adv": null,
            "bench": "HON&#39;BLE MS. JUSTICE BELA M. TRIVEDI, HON&#39;BLE MR. JUSTICE SATISH CHANDRA SHARMA",
            "judgement_by": "HON&#39;BLE MS. JUSTICE BELA M. TRIVEDI",
            "judgment_dates": "25-09-2024",
            "temp_link": "supremecourt/2015/13533/13533_2015_13_1501_56014_Judgement_25-Sep-2024.pdf (English)"
        },
        {
            "diary_no": "13707-2024",
            "Judgement_type": "J",
            "case_no": "Crl.A. No.-003978-003979 - 2024",
            "pet": "SUNIL @ SONU ETC.",
            "res": "STATE NCT OF DELHI",
            "pet_adv": "RISHI MALHOTRA",
            "res_adv": null,
            "bench": "HON&#39;BLE MR. JUSTICE B.R. GAVAI, HON&#39;BLE MR. JUSTICE K.V. VISWANATHAN",
            "judgement_by": "HON&#39;BLE MR. JUSTICE B.R. GAVAI",
            "judgment_dates": "24-09-2024",
            "temp_link": "supremecourt/2024/13707/13707_2024_3_1501_56022_Judgement_24-Sep-2024.pdf (English)"
        },
        {
            "diary_no": "13750-2011",
            "Judgement_type": "J",
            "case_no": "Crl.A. No.-001014-001015 - 2013",
            "pet": "PARVEEN KUMAR",
            "res": "THE STATE OF HIMACHAL PRADESH",
            "pet_adv": "PUSHKAR ANAND",
            "res_adv": "VIKRANT NARAYAN VASUDEVA",
            "bench": "HON&#39;BLE MS. JUSTICE BELA M. TRIVEDI, HON&#39;BLE MR. JUSTICE SATISH CHANDRA SHARMA",
            "judgement_by": "HON&#39;BLE MS. JUSTICE BELA M. TRIVEDI",
            "judgment_dates": "23-09-2024",
            "temp_link": "supremecourt/2011/13750/13750_2011_13_1501_55934_Judgement_23-Sep-2024.pdf (English)"
        },
        {
            "diary_no": "14305-2018",
            "Judgement_type": "J",
            "case_no": "Crl.A. No.-004003-004003 - 2024",
            "pet": "KAILASHBEN MAHENDRABHAI PATEL",
            "res": "THE STATE OF MAHARASHTRA",
            "pet_adv": "S. S. SHROFF",
            "res_adv": null,
            "bench": "HON&#39;BLE MR. JUSTICE PAMIDIGHANTAM SRI NARASIMHA, HON&#39;BLE MR. JUSTICE SANDEEP MEHTA",
            "judgement_by": "HON&#39;BLE MR. JUSTICE PAMIDIGHANTAM SRI NARASIMHA",
            "judgment_dates": "25-09-2024",
            "temp_link": "supremecourt/2018/14305/14305_2018_14_1501_55995_Judgement_25-Sep-2024.pdf (English)"
        },
        {
            "diary_no": "14307-2024",
            "Judgement_type": "J",
            "case_no": "CONMT.PET.(C) No.-000196-000197 - 2024",
            "pet": "M/S SITARAM ENTERPRISES",
            "res": "PRITHVIRAJ VARDICHAND JAIN",
            "pet_adv": "RAJEEV MAHESHWARANAND ROY",
            "res_adv": null,
            "bench": "HON&#39;BLE MR. JUSTICE J.K. MAHESHWARI, HON&#39;BLE MR. JUSTICE RAJESH BINDAL",
            "judgement_by": "HON&#39;BLE MR. JUSTICE J.K. MAHESHWARI",
            "judgment_dates": "09-09-2024",
            "temp_link": "supremecourt/2024/14307/14307_2024_8_60_55468_Judgement_09-Sep-2024.pdf (English)"
        },
        {
            "diary_no": "14765-2023",
            "Judgement_type": "J",
            "case_no": "Crl.A. No.-003923-003923 - 2024",
            "pet": "FULESHWAR GOPE",
            "res": "UNION OF INDIA",
            "pet_adv": "BALAJI SRINIVASAN",
            "res_adv": null,
            "bench": "HON&#39;BLE MR. JUSTICE C.T. RAVIKUMAR, HON&#39;BLE MR. JUSTICE SANJAY KAROL",
            "judgement_by": "HON&#39;BLE MR. JUSTICE C.T. RAVIKUMAR",
            "judgment_dates": "23-09-2024",
            "temp_link": "supremecourt/2023/14765/14765_2023_11_1501_55932_Judgement_23-Sep-2024.pdf (English)"
        },
        {
            "diary_no": "15069-2023",
            "Judgement_type": "J",
            "case_no": "Crl.A. No.-003747-003747 - 2024",
            "pet": "RAVINDER KUMAR",
            "res": "THE STATE OF HARYANA",
            "pet_adv": "VINEET BHAGAT",
            "res_adv": null,
            "bench": "HON&#39;BLE MR. JUSTICE ABHAY S. OKA, HON&#39;BLE MR. JUSTICE AHSANUDDIN AMANULLAH, HON&#39;BLE MR. JUSTICE AUGUSTINE GEORGE MASIH",
            "judgement_by": "HON&#39;BLE MR. JUSTICE ABHAY S. OKA",
            "judgment_dates": "12-09-2024",
            "temp_link": "supremecourt/2023/15069/15069_2023_6_1501_55514_Judgement_12-Sep-2024.pdf (English)"
        },
        {
            "diary_no": "15459-2013",
            "Judgement_type": "J",
            "case_no": "C.A. No.-010855-010855 - 2024",
            "pet": "PRAKASH BHALOTIA (D) THR HIS LRS",
            "res": "INDRA CHANDRA GOYAL (D) THRU.LRS",
            "pet_adv": "KUMAR DUSHYANT SINGH",
            "res_adv": "ANUPAM MISHRA",
            "bench": "HON&#39;BLE MR. JUSTICE J.K. MAHESHWARI, HON&#39;BLE MR. JUSTICE RAJESH BINDAL",
            "judgement_by": "HON&#39;BLE MR. JUSTICE J.K. MAHESHWARI",
            "judgment_dates": "25-09-2024",
            "temp_link": "supremecourt/2013/15459/15459_2013_8_11_56050_Judgement_25-Sep-2024.pdf (English)"
        },
        {
            "diary_no": "15840-2023",
            "Judgement_type": "J",
            "case_no": "Crl.A. No.-003989-003989 - 2024",
            "pet": "S VIJIKUMARI",
            "res": "MOWNESHWARACHARI C",
            "pet_adv": "N. SAI VINOD",
            "res_adv": null,
            "bench": "HON&#39;BLE MRS. JUSTICE B.V. NAGARATHNA, HON&#39;BLE MR. JUSTICE NONGMEIKAPAM KOTISWAR SINGH",
            "judgement_by": "HON&#39;BLE MRS. JUSTICE B.V. NAGARATHNA",
            "judgment_dates": "10-09-2024",
            "temp_link": "supremecourt/2023/15840/15840_2023_9_9_55546_Judgement_10-Sep-2024.pdf (English)"
        },
        {
            "diary_no": "17951-2023",
            "Judgement_type": "J",
            "case_no": "C.A. No.-003593-003594 - 2024",
            "pet": "RAJESH MITRA @ RAJESH KUMAR MITRA",
            "res": "KARNANI PROPERTIES LIMITED",
            "pet_adv": "RASHI BANSAL",
            "res_adv": null,
            "bench": "HON&#39;BLE MR. JUSTICE SUDHANSHU DHULIA, HON&#39;BLE MR. JUSTICE AHSANUDDIN AMANULLAH",
            "judgement_by": "HON&#39;BLE MR. JUSTICE SUDHANSHU DHULIA",
            "judgment_dates": "20-09-2024",
            "temp_link": "supremecourt/2023/17951/17951_2023_15_1501_55879_Judgement_20-Sep-2024.pdf (English)"
        },
        {
            "diary_no": "18273-2012",
            "Judgement_type": "J",
            "case_no": "Crl.A. No.-000249-000249 - 2013",
            "pet": "SHOOR SINGH ",
            "res": "STATE OF UTTARAKHAND",
            "pet_adv": "A. P. MOHANTY",
            "res_adv": "AKSHAT KUMAR",
            "bench": "HON&#39;BLE MR. JUSTICE J.B. PARDIWALA, HON&#39;BLE MR. JUSTICE MANOJ MISRA",
            "judgement_by": "HON&#39;BLE MR. JUSTICE MANOJ MISRA",
            "judgment_dates": "20-09-2024",
            "temp_link": "supremecourt/2012/18273/18273_2012_10_1501_55915_Judgement_20-Sep-2024.pdf (English)"
        },
        {
            "diary_no": "18524-2018",
            "Judgement_type": "J",
            "case_no": "C.A. No.-008343-008343 - 2024",
            "pet": "THE AHMEDNAGAR DISTRICT CENTRAL COOPERATIVE BANK LTD",
            "res": "THE STATE OF MAHARASHTRA",
            "pet_adv": "M. Y. DESHMUKH",
            "res_adv": null,
            "bench": "HON&#39;BLE MR. JUSTICE DIPANKAR DATTA, HON&#39;BLE MR. JUSTICE PRASHANT KUMAR MISHRA",
            "judgement_by": "HON&#39;BLE MR. JUSTICE DIPANKAR DATTA",
            "judgment_dates": "27-09-2024",
            "temp_link": "supremecourt/2018/18524/18524_2018_16_1501_56123_Judgement_27-Sep-2024.pdf (English)"
        },
        {
            "diary_no": "18885-2024",
            "Judgement_type": "J",
            "case_no": "Crl.A. No.-003883-003884 - 2024",
            "pet": "BHAGWAN SINGH",
            "res": "STATE OF U.P.",
            "pet_adv": "ANUBHAV ",
            "res_adv": null,
            "bench": "HON&#39;BLE MS. JUSTICE BELA M. TRIVEDI, HON&#39;BLE MR. JUSTICE SATISH CHANDRA SHARMA",
            "judgement_by": "HON&#39;BLE MS. JUSTICE BELA M. TRIVEDI",
            "judgment_dates": "20-09-2024",
            "temp_link": "supremecourt/2024/18885/18885_2024_13_1501_55877_Judgement_20-Sep-2024.pdf (English)"
        },
        {
            "diary_no": "19541-2022",
            "Judgement_type": "J",
            "case_no": "W.P.(Crl.) No.-000265 - 2022",
            "pet": "RABINA GHALE",
            "res": "UNION OF INDIA",
            "pet_adv": "AJIT SHARMA",
            "res_adv": null,
            "bench": "HON&#39;BLE MR. JUSTICE VIKRAM NATH, HON&#39;BLE  MR. JUSTICE PRASANNA B. VARALE",
            "judgement_by": "HON&#39;BLE MR. JUSTICE VIKRAM NATH",
            "judgment_dates": "17-09-2024",
            "temp_link": "supremecourt/2022/19541/19541_2022_7_1501_55692_Judgement_17-Sep-2024.pdf (English)"
        },
        {
            "diary_no": "19782-2020",
            "Judgement_type": "J",
            "case_no": "C.A. No.-005267-005267 - 2024",
            "pet": "ANDHRA PRADESH STATE ROAD TRANSPORT CORPORATION",
            "res": "V. V. BRAHMA REDDY",
            "pet_adv": "ASHISH KUMAR TIWARI ",
            "res_adv": null,
            "bench": "HON&#39;BLE MR. JUSTICE PAMIDIGHANTAM SRI NARASIMHA, HON&#39;BLE MR. JUSTICE SANDEEP MEHTA",
            "judgement_by": "HON&#39;BLE MR. JUSTICE PAMIDIGHANTAM SRI NARASIMHA",
            "judgment_dates": "06-09-2024",
            "temp_link": "supremecourt/2020/19782/19782_2020_14_1501_55380_Judgement_06-Sep-2024.pdf (English)"
        },
        {
            "diary_no": "20856-2024",
            "Judgement_type": "J",
            "case_no": "W.P.(C) No.-000312 - 2024",
            "pet": "CHIRAG BHANU SINGH",
            "res": "HIGH COURT OF HIMACHAL PRADESH",
            "pet_adv": " LAWYER S KNIT & CO",
            "res_adv": null,
            "bench": "HON&#39;BLE MR. JUSTICE HRISHIKESH ROY, HON&#39;BLE MR. JUSTICE PRASHANT KUMAR MISHRA",
            "judgement_by": "HON&#39;BLE MR. JUSTICE HRISHIKESH ROY",
            "judgment_dates": "06-09-2024",
            "temp_link": "supremecourt/2024/20856/20856_2024_5_1501_55488_Judgement_06-Sep-2024.pdf (English)"
        },
        {
            "diary_no": "21273-2012",
            "Judgement_type": "J",
            "case_no": "C.A. No.-005577-005577 - 2014",
            "pet": "MEERA DEVI (D) THR. LR.",
            "res": "DINESH CHANDRA JOSHI (D) THR. LRS",
            "pet_adv": "PRAVEEN SWARUP",
            "res_adv": "R. D. UPADHYAY",
            "bench": "HON&#39;BLE MR. JUSTICE J.K. MAHESHWARI, HON&#39;BLE MR. JUSTICE RAJESH BINDAL",
            "judgement_by": "HON&#39;BLE MR. JUSTICE RAJESH BINDAL",
            "judgment_dates": "19-09-2024",
            "temp_link": "supremecourt/2012/21273/21273_2012_8_1501_55753_Judgement_19-Sep-2024.pdf (English)"
        },
        {
            "diary_no": "21647-2020",
            "Judgement_type": "J",
            "case_no": "ARBIT.PETITON No.-000038 - 2020",
            "pet": "COX AND KINGS LTD.",
            "res": "SAP INDIA PVT. LTD.",
            "pet_adv": "DIVYAKANT LAHOTI",
            "res_adv": "DHEERAJ NAIR",
            "bench": "HON&#39;BLE THE CHIEF JUSTICE, HON&#39;BLE MR. JUSTICE J.B. PARDIWALA, HON&#39;BLE MR. JUSTICE MANOJ MISRA",
            "judgement_by": "HON&#39;BLE MR. JUSTICE J.B. PARDIWALA",
            "judgment_dates": "09-09-2024",
            "temp_link": "supremecourt/2020/21647/21647_2020_1_1502_55461_Judgement_09-Sep-2024.pdf (English)"
        },
        {
            "diary_no": "21674-2021",
            "Judgement_type": "J",
            "case_no": "Crl.A. No.-003727-003727 - 2024",
            "pet": "DEVENDRA KUMAR PAL",
            "res": "STATE OF U.P",
            "pet_adv": "PUNEET SINGH BINDRA",
            "res_adv": null,
            "bench": "HON&#39;BLE MR. JUSTICE B.R. GAVAI, HON&#39;BLE MR. JUSTICE K.V. VISWANATHAN",
            "judgement_by": "HON&#39;BLE MR. JUSTICE B.R. GAVAI",
            "judgment_dates": "06-09-2024",
            "temp_link": "supremecourt/2021/21674/21674_2021_3_41_55368_Judgement_06-Sep-2024.pdf (English)"
        },
        {
            "diary_no": "21735-2022",
            "Judgement_type": "J",
            "case_no": "Crl.A. No.-000806-000807 - 2023",
            "pet": "SHIVKUMAR RAMSUNDAR SAKET",
            "res": "THE STATE OF MAHARASHTRA",
            "pet_adv": "AMIT AGRAWAL",
            "res_adv": null,
            "bench": "HON&#39;BLE MR. JUSTICE B.R. GAVAI, HON&#39;BLE MR. JUSTICE PRASHANT KUMAR MISHRA, HON&#39;BLE MR. JUSTICE K.V. VISWANATHAN",
            "judgement_by": "HON&#39;BLE MR. JUSTICE B.R. GAVAI",
            "judgment_dates": "26-09-2024",
            "temp_link": "supremecourt/2022/21735/21735_2022_3_101_56006_Judgement_26-Sep-2024.pdf (English)"
        },
        {
            "diary_no": "21999-2022",
            "Judgement_type": "J",
            "case_no": "C.A. No.-010894-010894 - 2024",
            "pet": "SUB INSPECTOR SANJAY KUMAR",
            "res": "THE STATE OF UTTAR PRADESH",
            "pet_adv": "SYED MEHDI IMAM",
            "res_adv": null,
            "bench": "HON&#39;BLE MR. JUSTICE PAMIDIGHANTAM SRI NARASIMHA, HON&#39;BLE MR. JUSTICE SANDEEP MEHTA",
            "judgement_by": "HON&#39;BLE MR. JUSTICE SANDEEP MEHTA",
            "judgment_dates": "27-09-2024",
            "temp_link": "supremecourt/2022/21999/21999_2022_14_1502_56121_Judgement_27-Sep-2024.pdf (English)"
        },
        {
            "diary_no": "23024-2022",
            "Judgement_type": "J",
            "case_no": "C.A. No.-010440-010440 - 2024",
            "pet": "MANILAL",
            "res": "THE STATE OF RAJASTHAN",
            "pet_adv": "SAURABH AJAY GUPTA",
            "res_adv": null,
            "bench": "HON&#39;BLE MR. JUSTICE B.R. GAVAI, HON&#39;BLE MR. JUSTICE K.V. VISWANATHAN",
            "judgement_by": "HON&#39;BLE MR. JUSTICE K.V. VISWANATHAN",
            "judgment_dates": "10-09-2024",
            "temp_link": "supremecourt/2022/23024/23024_2022_3_1501_55540_Judgement_10-Sep-2024.pdf (English)"
        },
        {
            "diary_no": "23218-2021",
            "Judgement_type": "J",
            "case_no": "C.A. No.-010567-010567 - 2024",
            "pet": "S.D. MANOHARA",
            "res": "KONKAN RAILWAY CORPORATION LIMITED",
            "pet_adv": "ANIRUDH SANGANERIA",
            "res_adv": null,
            "bench": "HON&#39;BLE MR. JUSTICE PAMIDIGHANTAM SRI NARASIMHA, HON&#39;BLE MR. JUSTICE PANKAJ MITHAL",
            "judgement_by": "HON&#39;BLE MR. JUSTICE PAMIDIGHANTAM SRI NARASIMHA",
            "judgment_dates": "13-09-2024",
            "temp_link": "supremecourt/2021/23218/23218_2021_14_1501_55646_Judgement_13-Sep-2024.pdf (English)"
        },
        {
            "diary_no": "24030-2023",
            "Judgement_type": "J",
            "case_no": "C.A. No.-005735-005736 - 2023",
            "pet": "CHALASANI UDAYA SHANKAR",
            "res": "M/S LEXUS TECHNOLOGIES PVT. LTD",
            "pet_adv": "AMIT K. NAIN",
            "res_adv": null,
            "bench": "HON&#39;BLE THE CHIEF JUSTICE, HON&#39;BLE MR. JUSTICE SANJAY KUMAR",
            "judgement_by": "HON&#39;BLE THE CHIEF JUSTICE",
            "judgment_dates": "09-09-2024",
            "temp_link": "supremecourt/2023/24030/24030_2023_2_1501_55462_Judgement_09-Sep-2024.pdf (English)"
        },
        {
            "diary_no": "24154-2022",
            "Judgement_type": "J",
            "case_no": "C.A. No.-010662-010662 - 2024",
            "pet": "M/S ULTRA TECH CEMENT LIMITED",
            "res": "MAST RAM",
            "pet_adv": "E. C. AGRAWALA",
            "res_adv": null,
            "bench": "HON&#39;BLE THE CHIEF JUSTICE, HON&#39;BLE MR. JUSTICE J.B. PARDIWALA, HON&#39;BLE MR. JUSTICE MANOJ MISRA",
            "judgement_by": "HON&#39;BLE MR. JUSTICE J.B. PARDIWALA",
            "judgment_dates": "20-09-2024",
            "temp_link": "supremecourt/2022/24154/24154_2022_1_1501_55866_Judgement_20-Sep-2024.pdf (English)"
        },
        {
            "diary_no": "24404-2017",
            "Judgement_type": "J",
            "case_no": "C.A. No.-010889-010889 - 2024",
            "pet": "PUNJAB STATE CIVIL SUPPLIES CORPORATION LTD.",
            "res": "M/S. SANMAN RICE MILLS",
            "pet_adv": null,
            "res_adv": null,
            "bench": "HON&#39;BLE MR. JUSTICE PANKAJ MITHAL, HON&#39;BLE MR. JUSTICE R. MAHADEVAN",
            "judgement_by": "HON&#39;BLE MR. JUSTICE PANKAJ MITHAL",
            "judgment_dates": "27-09-2024",
            "temp_link": "supremecourt/2017/24404/24404_2017_17_1501_56124_Judgement_27-Sep-2024.pdf (English)"
        },
        {
            "diary_no": "25168-2015",
            "Judgement_type": "J",
            "case_no": "C.A. No.-009731-009732 - 2024",
            "pet": "LAKSHMESH M.",
            "res": "P. RAJALAKSHMI (DEAD BY LRS.) AND ORS.  ETC ETC",
            "pet_adv": "D. L. CHIDANANDA",
            "res_adv": null,
            "bench": "HON&#39;BLE MR. JUSTICE ABHAY S. OKA, HON&#39;BLE MR. JUSTICE AHSANUDDIN AMANULLAH, HON&#39;BLE MR. JUSTICE AUGUSTINE GEORGE MASIH",
            "judgement_by": "HON&#39;BLE MR. JUSTICE ABHAY S. OKA",
            "judgment_dates": "11-09-2024",
            "temp_link": "supremecourt/2015/25168/25168_2015_6_1501_55513_Judgement_11-Sep-2024.pdf (English)"
        },
        {
            "diary_no": "25402-2023",
            "Judgement_type": "J",
            "case_no": "Crl.A. No.-003821-003821 - 2023",
            "pet": "SOMPRABHA RANA",
            "res": "THE STATE OF MADHYA PRADESH",
            "pet_adv": "NIKHIL JAIN",
            "res_adv": null,
            "bench": "HON&#39;BLE MR. JUSTICE ABHAY S. OKA, HON&#39;BLE MR. JUSTICE AUGUSTINE GEORGE MASIH",
            "judgement_by": "HON&#39;BLE MR. JUSTICE ABHAY S. OKA",
            "judgment_dates": "06-09-2024",
            "temp_link": "supremecourt/2023/25402/25402_2023_6_1501_55374_Judgement_06-Sep-2024.pdf (English)"
        },
        {
            "diary_no": "26126-2021",
            "Judgement_type": "J",
            "case_no": "C.A. No.-010038-010038 - 2024",
            "pet": "N.M. THEERTHEGOWDA",
            "res": "Y.M. ASHOK KUMAR",
            "pet_adv": "CHAND QURESHI",
            "res_adv": null,
            "bench": "HON&#39;BLE MR. JUSTICE HRISHIKESH ROY, HON&#39;BLE MR. JUSTICE S.V.N. BHATTI",
            "judgement_by": "HON&#39;BLE MR. JUSTICE S.V.N. BHATTI",
            "judgment_dates": "02-09-2024",
            "temp_link": "supremecourt/2021/26126/26126_2021_5_1501_55218_Judgement_02-Sep-2024.pdf (English)"
        },
        {
            "diary_no": "26296-2011",
            "Judgement_type": "J",
            "case_no": "Crl.A. No.-001614-001618 - 2012",
            "pet": "MANIK",
            "res": "THE STATE OF MAHARASHTRA",
            "pet_adv": "SHIVAJI M. JADHAV",
            "res_adv": "AADITYA ANIRUDDHA PANDE",
            "bench": "",
            "judgement_by": "HON&#39;BLE MR. JUSTICE C.T. RAVIKUMAR",
            "judgment_dates": "25-09-2024",
            "temp_link": "supremecourt/2011/26296/26296_2011_11_1501_56155_Judgement_25-Sep-2024.pdf (English)"
        },
        {
            "diary_no": "26346-2018",
            "Judgement_type": "J",
            "case_no": "C.A. No.-010893-010893 - 2024",
            "pet": "LAKHA SINGH",
            "res": "BALWINDER SINGH",
            "pet_adv": "ANKIT GOEL",
            "res_adv": null,
            "bench": "HON&#39;BLE MR. JUSTICE PAMIDIGHANTAM SRI NARASIMHA, HON&#39;BLE MR. JUSTICE SANDEEP MEHTA",
            "judgement_by": "HON&#39;BLE MR. JUSTICE SANDEEP MEHTA",
            "judgment_dates": "27-09-2024",
            "temp_link": "supremecourt/2018/26346/26346_2018_14_1501_56121_Judgement_27-Sep-2024.pdf (English)"
        },
        {
            "diary_no": "26726-2015",
            "Judgement_type": "J",
            "case_no": "C.A. No.-002459-002459 - 2017",
            "pet": "UNION OF INDIA",
            "res": "LT. COL RAHUL ARORA",
            "pet_adv": "MUKESH KUMAR MARORIA",
            "res_adv": null,
            "bench": "HON&#39;BLE MR. JUSTICE DIPANKAR DATTA, HON&#39;BLE MR. JUSTICE PRASHANT KUMAR MISHRA",
            "judgement_by": "HON&#39;BLE MR. JUSTICE PRASHANT KUMAR MISHRA",
            "judgment_dates": "09-09-2024",
            "temp_link": "supremecourt/2015/26726/26726_2015_16_1501_55475_Judgement_09-Sep-2024.pdf (English)"
        },
        {
            "diary_no": "27078-2022",
            "Judgement_type": "J",
            "case_no": "Crl.A. No.-002294-002294 - 2024",
            "pet": "LAV KUMAR @ KANHIYA",
            "res": "THE STATE OF UTTAR PRADESH",
            "pet_adv": "V. MAHESHWARI & CO.",
            "res_adv": null,
            "bench": "HON&#39;BLE THE CHIEF JUSTICE, HON&#39;BLE MR. JUSTICE SANJAY KUMAR, HON&#39;BLE MR. JUSTICE R. MAHADEVAN",
            "judgement_by": "HON&#39;BLE THE CHIEF JUSTICE",
            "judgment_dates": "12-09-2024",
            "temp_link": "supremecourt/2022/27078/27078_2022_2_101_55557_Judgement_12-Sep-2024.pdf (English)"
        },
        {
            "diary_no": "27435-2013",
            "Judgement_type": "J",
            "case_no": "C.A. No.-008387-008387 - 2013",
            "pet": "UNION OF INDIA",
            "res": "SHRI DOLY LOYI",
            "pet_adv": null,
            "res_adv": "SURINDER KUMAR GUPTA",
            "bench": "HON&#39;BLE MR. JUSTICE PAMIDIGHANTAM SRI NARASIMHA, HON&#39;BLE MR. JUSTICE SANDEEP MEHTA",
            "judgement_by": "HON&#39;BLE MR. JUSTICE PAMIDIGHANTAM SRI NARASIMHA",
            "judgment_dates": "24-09-2024",
            "temp_link": "supremecourt/2013/27435/27435_2013_14_1501_56031_Judgement_24-Sep-2024.pdf (English)"
        },
        {
            "diary_no": "28491-2021",
            "Judgement_type": "J",
            "case_no": "C.A. No.-003981-003982 - 2024",
            "pet": "OPG POWER GENERATION PRIVATE LIMITED",
            "res": "ENEXIO POWER COOLING SOLUTIONS INDIA PRIVATE LIMITED",
            "pet_adv": "AMAN GUPTA",
            "res_adv": null,
            "bench": "HON&#39;BLE THE CHIEF JUSTICE, HON&#39;BLE MR. JUSTICE J.B. PARDIWALA, HON&#39;BLE MR. JUSTICE MANOJ MISRA",
            "judgement_by": "HON&#39;BLE MR. JUSTICE MANOJ MISRA",
            "judgment_dates": "20-09-2024",
            "temp_link": "supremecourt/2021/28491/28491_2021_1_1503_55866_Judgement_20-Sep-2024.pdf (English)"
        },
        {
            "diary_no": "28673-2011",
            "Judgement_type": "J",
            "case_no": "Crl.A. No.-000313-000314 - 2012",
            "pet": "SAHEB S/O MAROTI BHUMRE",
            "res": "THE STATE OF MAHARASHTRA",
            "pet_adv": "VATSALYA VIGYA",
            "res_adv": "AADITYA ANIRUDDHA PANDE",
            "bench": "HON&#39;BLE THE CHIEF JUSTICE, HON&#39;BLE MR. JUSTICE SANJAY KUMAR, HON&#39;BLE MR. JUSTICE R. MAHADEVAN",
            "judgement_by": "HON&#39;BLE MR. JUSTICE SANJAY KUMAR",
            "judgment_dates": "18-09-2024",
            "temp_link": "supremecourt/2011/28673/28673_2011_2_1501_55758_Judgement_18-Sep-2024.pdf (English)"
        },
        {
            "diary_no": "28723-2023",
            "Judgement_type": "J",
            "case_no": "MA-001861 - 2023",
            "pet": "GAGAN BANGA",
            "res": "THE STATE OF WEST BENGAL",
            "pet_adv": "TALHA ABDUL RAHMAN",
            "res_adv": null,
            "bench": "HON&#39;BLE MR. JUSTICE SANJAY KUMAR, HON&#39;BLE MR. JUSTICE ARAVIND KUMAR",
            "judgement_by": "HON&#39;BLE THE CHIEF JUSTICE",
            "judgment_dates": "23-09-2024",
            "temp_link": "supremecourt/2023/28723/28723_2023_2_1501_55924_Judgement_23-Sep-2024.pdf (English)"
        },
        {
            "diary_no": "29120-2011",
            "Judgement_type": "J",
            "case_no": "Crl.A. No.-001467-001467 - 2012",
            "pet": "RAMESH",
            "res": "THE STATE OF KARNATAKA HOME DEPARTMENT SECRETARY",
            "pet_adv": " DEVASA & CO.",
            "res_adv": null,
            "bench": "HON&#39;BLE THE CHIEF JUSTICE, HON&#39;BLE MR. JUSTICE SANJAY KUMAR, HON&#39;BLE MR. JUSTICE R. MAHADEVAN",
            "judgement_by": "HON&#39;BLE MR. JUSTICE SANJAY KUMAR",
            "judgment_dates": "18-09-2024",
            "temp_link": "supremecourt/2011/29120/29120_2011_2_1502_55758_Judgement_18-Sep-2024.pdf (English)"
        },
        {
            "diary_no": "29455-2012",
            "Judgement_type": "J",
            "case_no": "C.A. No.-007262-007262 - 2012",
            "pet": "P.N.GUPTA",
            "res": "RAJINDER SINGH DOGRA",
            "pet_adv": "T. MAHIPAL",
            "res_adv": "SUBHASISH BHOWMICK",
            "bench": "HON&#39;BLE MR. JUSTICE PAMIDIGHANTAM SRI NARASIMHA, HON&#39;BLE MR. JUSTICE SANDEEP MEHTA",
            "judgement_by": "HON&#39;BLE MR. JUSTICE PAMIDIGHANTAM SRI NARASIMHA",
            "judgment_dates": "05-09-2024",
            "temp_link": "supremecourt/2012/29455/29455_2012_14_101_55332_Judgement_05-Sep-2024.pdf (English)"
        },
        {
            "diary_no": "29859-2011",
            "Judgement_type": "J",
            "case_no": "Crl.A. No.-000477-000477 - 2017",
            "pet": "YOGARANI",
            "res": "STATE  BY INSPECTOR OF POLICE",
            "pet_adv": "DEEPAK ANAND",
            "res_adv": "MUKESH KUMAR MARORIA",
            "bench": "HON&#39;BLE MR. JUSTICE M.M. SUNDRESH, HON&#39;BLE MR. JUSTICE ARAVIND KUMAR",
            "judgement_by": "HON&#39;BLE MR. JUSTICE ARAVIND KUMAR",
            "judgment_dates": "23-09-2024",
            "temp_link": "supremecourt/2011/29859/29859_2011_12_1501_55933_Judgement_23-Sep-2024.pdf (English)"
        },
        {
            "diary_no": "30014-2021",
            "Judgement_type": "J",
            "case_no": "C.A. No.-010648-010648 - 2024",
            "pet": "SUSHMA",
            "res": "NITIN GANAPATI RANGOLE",
            "pet_adv": "SESHATALPA SAI BANDARU",
            "res_adv": null,
            "bench": "HON&#39;BLE MR. JUSTICE PAMIDIGHANTAM SRI NARASIMHA, HON&#39;BLE MR. JUSTICE SANDEEP MEHTA",
            "judgement_by": "HON&#39;BLE MR. JUSTICE SANDEEP MEHTA",
            "judgment_dates": "19-09-2024",
            "temp_link": "supremecourt/2021/30014/30014_2021_14_1501_55860_Judgement_19-Sep-2024.pdf (English)"
        },
        {
            "diary_no": "30716-2016",
            "Judgement_type": "J",
            "case_no": "C.A. No.-001511-001513 - 2021",
            "pet": "SUKHMANDER SINGH AND ORS ETC ETC",
            "res": "THE STATE OF PUNJAB AND ORS ETC ETC.",
            "pet_adv": "VIJAY KASANA",
            "res_adv": "KAILASH CHAND",
            "bench": "HON&#39;BLE MR. JUSTICE HRISHIKESH ROY, HON&#39;BLE MR. JUSTICE SUDHANSHU DHULIA, HON&#39;BLE MR. JUSTICE S.V.N. BHATTI",
            "judgement_by": "HON&#39;BLE MR. JUSTICE HRISHIKESH ROY",
            "judgment_dates": "11-09-2024",
            "temp_link": "supremecourt/2016/30716/30716_2016_5_102_55564_Judgement_11-Sep-2024.pdf (English)"
        },
        {
            "diary_no": "32065-2013",
            "Judgement_type": "J",
            "case_no": "C.A. No.-002394-002394 - 2023",
            "pet": "RANJIT SINGH ",
            "res": "STATE OF UTTARAKHAND &AMP; ORS",
            "pet_adv": "RACHNA GUPTA",
            "res_adv": null,
            "bench": "HON&#39;BLE MR. JUSTICE ABHAY S. OKA, HON&#39;BLE MR. JUSTICE AHSANUDDIN AMANULLAH, HON&#39;BLE MR. JUSTICE AUGUSTINE GEORGE MASIH",
            "judgement_by": "HON&#39;BLE MR. JUSTICE ABHAY S. OKA",
            "judgment_dates": "12-09-2024",
            "temp_link": "supremecourt/2013/32065/32065_2013_6_111_55514_Judgement_12-Sep-2024.pdf (English)"
        },
        {
            "diary_no": "35014-2022",
            "Judgement_type": "J",
            "case_no": "SLP(C) No.-020817 - 2022",
            "pet": "KERALA AGRICULTURAL UNIVERSITY",
            "res": "T. P. MURALI @ MURALI THAVARA PANEN",
            "pet_adv": "P. I. JOSE",
            "res_adv": null,
            "bench": "HON&#39;BLE MR. JUSTICE PANKAJ MITHAL, HON&#39;BLE MR. JUSTICE R. MAHADEVAN",
            "judgement_by": "HON&#39;BLE MR. JUSTICE PANKAJ MITHAL",
            "judgment_dates": "04-09-2024",
            "temp_link": "supremecourt/2022/35014/35014_2022_16_1501_55338_Judgement_04-Sep-2024.pdf (English)"
        },
        {
            "diary_no": "35595-2023",
            "Judgement_type": "J",
            "case_no": "C.A. No.-010549-010549 - 2024",
            "pet": "KIMNEO HAOKIP HANGSHING",
            "res": "KENN RAIKHAN",
            "pet_adv": "B. KRISHNA PRASAD",
            "res_adv": null,
            "bench": "HON&#39;BLE MR. JUSTICE SUDHANSHU DHULIA, HON&#39;BLE MR. JUSTICE AHSANUDDIN AMANULLAH",
            "judgement_by": "HON&#39;BLE MR. JUSTICE SUDHANSHU DHULIA",
            "judgment_dates": "13-09-2024",
            "temp_link": "supremecourt/2023/35595/35595_2023_15_1501_55647_Judgement_13-Sep-2024.pdf (English)"
        },
        {
            "diary_no": "36231-2024",
            "Judgement_type": "J",
            "case_no": "Crl.A. No.-003816-003816 - 2024",
            "pet": "ARVIND KEJRIWAL",
            "res": "CENTRAL BUREAU OF INVESTIGATION",
            "pet_adv": "VIVEK JAIN",
            "res_adv": null,
            "bench": "HON&#39;BLE MR. JUSTICE SURYA KANT, HON&#39;BLE MR. JUSTICE UJJAL BHUYAN",
            "judgement_by": "HON&#39;BLE MR. JUSTICE SURYA KANT",
            "judgment_dates": "13-09-2024",
            "temp_link": "supremecourt/2024/36231/36231_2024_4_1501_55638_Judgement_13-Sep-2024.pdf (English)"
        },
        {
            "diary_no": "36425-2023",
            "Judgement_type": "J",
            "case_no": "Crl.A. No.-003738-003738 - 2024",
            "pet": "MANDAKINI DIWAN",
            "res": "THE HIGH COURT OF CHHATTISGARH",
            "pet_adv": "DHAWESH PAHUJA",
            "res_adv": null,
            "bench": "HON&#39;BLE MR. JUSTICE VIKRAM NATH, HON&#39;BLE  MR. JUSTICE PRASANNA B. VARALE",
            "judgement_by": "HON&#39;BLE MR. JUSTICE VIKRAM NATH",
            "judgment_dates": "06-09-2024",
            "temp_link": "supremecourt/2023/36425/36425_2023_7_1501_55375_Judgement_06-Sep-2024.pdf (English)"
        },
        {
            "diary_no": "36958-2024",
            "Judgement_type": "J",
            "case_no": "SLP(C) No.-019953 - 2024",
            "pet": "SAHIL BHARGAVA",
            "res": "STATE OF UTTARAKHAND",
            "pet_adv": "RAGHAV SABHARWAL ",
            "res_adv": null,
            "bench": "HON&#39;BLE THE CHIEF JUSTICE, HON&#39;BLE MR. JUSTICE J.B. PARDIWALA, HON&#39;BLE MR. JUSTICE MANOJ MISRA",
            "judgement_by": "HON&#39;BLE THE CHIEF JUSTICE",
            "judgment_dates": "09-09-2024",
            "temp_link": "supremecourt/2024/36958/36958_2024_1_34_55461_Judgement_09-Sep-2024.pdf (English)"
        },
        {
            "diary_no": "37080-2023",
            "Judgement_type": "J",
            "case_no": "C.A. No.-010913-010913 - 2024",
            "pet": "MANISHA RAVINDRA PANPATIL",
            "res": "THE STATE OF MAHARASHTRA",
            "pet_adv": "VATSALYA VIGYA",
            "res_adv": null,
            "bench": "HON&#39;BLE MR. JUSTICE SURYA KANT, HON&#39;BLE MR. JUSTICE UJJAL BHUYAN",
            "judgement_by": "HON&#39;BLE MR. JUSTICE SURYA KANT",
            "judgment_dates": "27-09-2024",
            "temp_link": "supremecourt/2023/37080/37080_2023_4_40_56112_Judgement_27-Sep-2024.pdf (English)"
        },
        {
            "diary_no": "37354-2024",
            "Judgement_type": "J",
            "case_no": "W.P.(C) No.-000551-000551 - 2024",
            "pet": "ASHOK KUMAR SHARMA",
            "res": "UNION OF INDIA",
            "pet_adv": "PRASHANT BHUSHAN",
            "res_adv": null,
            "bench": "HON&#39;BLE THE CHIEF JUSTICE, HON&#39;BLE MR. JUSTICE J.B. PARDIWALA, HON&#39;BLE MR. JUSTICE MANOJ MISRA",
            "judgement_by": "HON&#39;BLE THE CHIEF JUSTICE",
            "judgment_dates": "09-09-2024",
            "temp_link": "supremecourt/2024/37354/37354_2024_1_12_55461_Judgement_09-Sep-2024.pdf (English)"
        },
        {
            "diary_no": "37375-2024",
            "Judgement_type": "J",
            "case_no": "C.A. No.-009958 - 2024",
            "pet": "RICARDO CONSTRUCTIONS PVT. LTD.",
            "res": "RAVI KUCKIAN",
            "pet_adv": "VAIBHAV NITI",
            "res_adv": null,
            "bench": "HON&#39;BLE MR. JUSTICE J.K. MAHESHWARI, HON&#39;BLE MR. JUSTICE RAJESH BINDAL",
            "judgement_by": "HON&#39;BLE MR. JUSTICE J.K. MAHESHWARI",
            "judgment_dates": "06-09-2024",
            "temp_link": "supremecourt/2024/37375/37375_2024_8_28_55376_Judgement_06-Sep-2024.pdf (English)"
        },
        {
            "diary_no": "37724-2024",
            "Judgement_type": "J",
            "case_no": "C.A. No.-010046-010047 - 2024",
            "pet": "KERALA STATE ELECTRICITY BOARD LTD.",
            "res": "JHABUA POWER LIMITED",
            "pet_adv": "PRABHAS BAJAJ",
            "res_adv": null,
            "bench": "HON&#39;BLE THE CHIEF JUSTICE, HON&#39;BLE MR. JUSTICE J.B. PARDIWALA, HON&#39;BLE MR. JUSTICE MANOJ MISRA",
            "judgement_by": "HON&#39;BLE THE CHIEF JUSTICE",
            "judgment_dates": "30-09-2024",
            "temp_link": "supremecourt/2024/37724/37724_2024_1_34_56159_Judgement_30-Sep-2024.pdf (English)"
        },
        {
            "diary_no": "37806-2012",
            "Judgement_type": "J",
            "case_no": "Crl.A. No.-001348-001348 - 2014",
            "pet": "NITYA NAND",
            "res": "STATE OF UTTAR PRADESH",
            "pet_adv": "P. K. JAIN",
            "res_adv": null,
            "bench": "HON&#39;BLE MR. JUSTICE SURYA KANT, HON&#39;BLE MR. JUSTICE UJJAL BHUYAN",
            "judgement_by": "HON&#39;BLE MR. JUSTICE SURYA KANT",
            "judgment_dates": "04-09-2024",
            "temp_link": "supremecourt/2012/37806/37806_2012_4_1501_55449_Judgement_04-Sep-2024.pdf (English)"
        },
        {
            "diary_no": "38050-2011",
            "Judgement_type": "J",
            "case_no": "Crl.A. No.-001389-001389 - 2012",
            "pet": "BALJINDER SINGH @ LADOO",
            "res": "THE STATE OF PUNJAB",
            "pet_adv": "SANJAY JAIN",
            "res_adv": null,
            "bench": "HON&#39;BLE MR. JUSTICE SURYA KANT, HON&#39;BLE MR. JUSTICE DIPANKAR DATTA, HON&#39;BLE MR. JUSTICE UJJAL BHUYAN",
            "judgement_by": "HON&#39;BLE MR. JUSTICE DIPANKAR DATTA",
            "judgment_dates": "25-09-2024",
            "temp_link": "supremecourt/2011/38050/38050_2011_4_1502_56057_Judgement_25-Sep-2024.pdf (English)"
        },
        {
            "diary_no": "38111-2019",
            "Judgement_type": "J",
            "case_no": "SLP(C) No.-026454 - 2019",
            "pet": "KHURSHEED",
            "res": "SHAQOOR",
            "pet_adv": "DIVYA ROY",
            "res_adv": null,
            "bench": "HON&#39;BLE MR. JUSTICE SUDHANSHU DHULIA, HON&#39;BLE MR. JUSTICE AHSANUDDIN AMANULLAH",
            "judgement_by": "HON&#39;BLE MR. JUSTICE SUDHANSHU DHULIA",
            "judgment_dates": "10-09-2024",
            "temp_link": "supremecourt/2019/38111/38111_2019_15_37_55552_Judgement_10-Sep-2024.pdf (English)"
        },
        {
            "diary_no": "38164-2024",
            "Judgement_type": "J",
            "case_no": "SLP(C) No.-020243 - 2024",
            "pet": "TALLURI SRIKAR THROUGH HIS FATHER TALLURI SRIKRISHNA",
            "res": "THE DIRECTOR, NATIONAL TESTING AGENCY",
            "pet_adv": "PETITIONER-IN-PERSON",
            "res_adv": null,
            "bench": "HON&#39;BLE THE CHIEF JUSTICE, HON&#39;BLE MR. JUSTICE J.B. PARDIWALA, HON&#39;BLE MR. JUSTICE MANOJ MISRA",
            "judgement_by": "HON&#39;BLE MR. JUSTICE MANOJ MISRA",
            "judgment_dates": "13-09-2024",
            "temp_link": "supremecourt/2024/38164/38164_2024_1_1501_55636_Judgement_13-Sep-2024.pdf (English)"
        },
        {
            "diary_no": "39692-2013",
            "Judgement_type": "J",
            "case_no": "C.A. No.-000613-000613 - 2017",
            "pet": "JANARDAN DAS .",
            "res": "DURGA PRASAD AGRAWALLA .",
            "pet_adv": "SIBO SANKAR MISHRA",
            "res_adv": null,
            "bench": "HON&#39;BLE MR. JUSTICE VIKRAM NATH, HON&#39;BLE MR. JUSTICE PANKAJ MITHAL, HON&#39;BLE  MR. JUSTICE PRASANNA B. VARALE",
            "judgement_by": "HON&#39;BLE MR. JUSTICE VIKRAM NATH",
            "judgment_dates": "26-09-2024",
            "temp_link": "supremecourt/2013/39692/39692_2013_7_101_56036_Judgement_26-Sep-2024.pdf (English)"
        },
        {
            "diary_no": "40436-2022",
            "Judgement_type": "J",
            "case_no": "SLP(C) No.-003056 - 2023",
            "pet": "CHOUDAPPA",
            "res": "CHOUDAPPA SINCE DECEASED BY LRS.",
            "pet_adv": "VIKRAM HEGDE",
            "res_adv": null,
            "bench": "HON&#39;BLE MR. JUSTICE PANKAJ MITHAL, HON&#39;BLE MR. JUSTICE R. MAHADEVAN",
            "judgement_by": "HON&#39;BLE MR. JUSTICE PANKAJ MITHAL",
            "judgment_dates": "03-09-2024",
            "temp_link": "supremecourt/2022/40436/40436_2022_17_27_55297_Judgement_03-Sep-2024.pdf (English)"
        },
        {
            "diary_no": "41339-2019",
            "Judgement_type": "J",
            "case_no": "C.A. No.-010472-010472 - 2024",
            "pet": "R. P. GARG",
            "res": "THE CHIEF GENERAL MANAGER TELECOM DEPARTMENT",
            "pet_adv": "BUSHRA PARVEEN ",
            "res_adv": null,
            "bench": "HON&#39;BLE MR. JUSTICE PAMIDIGHANTAM SRI NARASIMHA, HON&#39;BLE MR. JUSTICE SANDEEP MEHTA",
            "judgement_by": "HON&#39;BLE MR. JUSTICE PAMIDIGHANTAM SRI NARASIMHA",
            "judgment_dates": "10-09-2024",
            "temp_link": "supremecourt/2019/41339/41339_2019_14_48_55551_Judgement_10-Sep-2024.pdf (English)"
        },
        {
            "diary_no": "41368-2023",
            "Judgement_type": "J",
            "case_no": "MA-000261 - 2024",
            "pet": "THE STATE OF MADHYA PRADESH",
            "res": "RAMJI LAL SHARMA",
            "pet_adv": "YASHRAJ SINGH BUNDELA ",
            "res_adv": null,
            "bench": "HON&#39;BLE MRS. JUSTICE B.V. NAGARATHNA, HON&#39;BLE MR. JUSTICE NONGMEIKAPAM KOTISWAR SINGH",
            "judgement_by": "HON&#39;BLE MRS. JUSTICE B.V. NAGARATHNA",
            "judgment_dates": "23-09-2024",
            "temp_link": "supremecourt/2023/41368/41368_2023_9_31_55931_Judgement_23-Sep-2024.pdf (English)"
        },
        {
            "diary_no": "41434-2019",
            "Judgement_type": "J",
            "case_no": "C.A. No.-010812-010812 - 2024",
            "pet": "DINESH GOYAL @ PAPPU",
            "res": "SUMAN AGARWAL (BINDAL)",
            "pet_adv": "CHRISTI JAIN",
            "res_adv": null,
            "bench": "HON&#39;BLE MR. JUSTICE C.T. RAVIKUMAR, HON&#39;BLE MR. JUSTICE SANJAY KAROL",
            "judgement_by": "HON&#39;BLE MR. JUSTICE C.T. RAVIKUMAR",
            "judgment_dates": "24-09-2024",
            "temp_link": "supremecourt/2019/41434/41434_2019_11_1501_56029_Judgement_24-Sep-2024.pdf (English)"
        },
        {
            "diary_no": "41496-2023",
            "Judgement_type": "J",
            "case_no": "C.A. No.-010620-010620 - 2024",
            "pet": "ROHAN BUILDERS (INDIA) PRIVATE LIMITED",
            "res": "BERGER PAINTS INDIA LIMITED",
            "pet_adv": "UDITA SINGH",
            "res_adv": null,
            "bench": "HON&#39;BLE THE CHIEF JUSTICE, HON&#39;BLE MR. JUSTICE SANJAY KUMAR, HON&#39;BLE MR. JUSTICE R. MAHADEVAN",
            "judgement_by": "HON&#39;BLE THE CHIEF JUSTICE",
            "judgment_dates": "12-09-2024",
            "temp_link": "supremecourt/2023/41496/41496_2023_2_1501_55557_Judgement_12-Sep-2024.pdf (English)"
        },
        {
            "diary_no": "41565-2023",
            "Judgement_type": "J",
            "case_no": "Crl.A. No.-003680-003682 - 2024",
            "pet": "RANJEET MITTAL",
            "res": "THE STATE OF MADHYA PRADESH",
            "pet_adv": "PRAVEEN SWARUP",
            "res_adv": null,
            "bench": "HON&#39;BLE MR. JUSTICE VIKRAM NATH, HON&#39;BLE  MR. JUSTICE PRASANNA B. VARALE",
            "judgement_by": "HON&#39;BLE MR. JUSTICE VIKRAM NATH",
            "judgment_dates": "03-09-2024",
            "temp_link": "supremecourt/2023/41565/41565_2023_7_28_55286_Judgement_03-Sep-2024.pdf (English)"
        },
        {
            "diary_no": "42573-2023",
            "Judgement_type": "J",
            "case_no": "Crl.A. No.-003216-003216 - 2024",
            "pet": "BACCAROSE PERFUMES AND BEAUTY PRODUCTS PVT. LTD.",
            "res": "CENTRAL BUREAU OF INVESTIGATION",
            "pet_adv": "SHAMIK SHIRISHBHAI SANJANWALA",
            "res_adv": null,
            "bench": "HON&#39;BLE MR. JUSTICE ABHAY S. OKA, HON&#39;BLE MR. JUSTICE AUGUSTINE GEORGE MASIH",
            "judgement_by": "HON&#39;BLE MR. JUSTICE ABHAY S. OKA",
            "judgment_dates": "06-09-2024",
            "temp_link": "supremecourt/2023/42573/42573_2023_6_1502_55374_Judgement_06-Sep-2024.pdf (English)"
        },
        {
            "diary_no": "43434-2019",
            "Judgement_type": "J",
            "case_no": "C.A. No.-010805-010806 - 2024",
            "pet": "HMT LTD.",
            "res": "RUKMINI",
            "pet_adv": "ANKIT KUMAR LAL",
            "res_adv": null,
            "bench": "HON&#39;BLE THE CHIEF JUSTICE, HON&#39;BLE MR. JUSTICE SANJAY KUMAR",
            "judgement_by": "HON&#39;BLE THE CHIEF JUSTICE",
            "judgment_dates": "24-09-2024",
            "temp_link": "supremecourt/2019/43434/43434_2019_2_1501_56021_Judgement_24-Sep-2024.pdf (English)"
        },
        {
            "diary_no": "43463-2024",
            "Judgement_type": "J",
            "case_no": "W.P.(C) No.-000609-000609 - 2024",
            "pet": "ATUL KUMAR",
            "res": "THE CHAIRMAN (JOINT SEAT ALLOCATION AUTHORITY)",
            "pet_adv": "PRAGYA BAGHEL",
            "res_adv": null,
            "bench": "HON&#39;BLE THE CHIEF JUSTICE, HON&#39;BLE MR. JUSTICE J.B. PARDIWALA, HON&#39;BLE MR. JUSTICE MANOJ MISRA",
            "judgement_by": "HON&#39;BLE THE CHIEF JUSTICE",
            "judgment_dates": "30-09-2024",
            "temp_link": "supremecourt/2024/43463/43463_2024_1_61_56159_Judgement_30-Sep-2024.pdf (English)"
        },
        {
            "diary_no": "43542-2023",
            "Judgement_type": "J",
            "case_no": "C.A. No.-010545-010545 - 2024",
            "pet": "RASHMI KANT VIJAY CHANDRA",
            "res": "BAIJNATH CHOUBEY AND COMPANY",
            "pet_adv": "SARAD KUMAR SINGHANIA",
            "res_adv": null,
            "bench": "HON&#39;BLE MR. JUSTICE C.T. RAVIKUMAR, HON&#39;BLE MR. JUSTICE SANJAY KAROL",
            "judgement_by": "HON&#39;BLE MR. JUSTICE C.T. RAVIKUMAR",
            "judgment_dates": "13-09-2024",
            "temp_link": "supremecourt/2023/43542/43542_2023_11_1501_55649_Judgement_13-Sep-2024.pdf (English)"
        },
        {
            "diary_no": "43583-2024",
            "Judgement_type": "J",
            "case_no": "SMW(C) No.-000009-000009 - 2024",
            "pet": "IN RE: REMARKS BY HIGH COURT JUDGE DURING COURT PROCEEDINGS",
            "res": "",
            "pet_adv": "BY COURTS MOTION",
            "res_adv": null,
            "bench": "HON&#39;BLE THE CHIEF JUSTICE, HON&#39;BLE THE CHIEF JUSTICE, HON&#39;BLE MR. JUSTICE B.R. GAVAI, HON&#39;BLE MR. JUSTICE SURYA KANT, HON&#39;BLE MR. JUSTICE HRISHIKESH ROY",
            "judgement_by": "HON&#39;BLE THE CHIEF JUSTICE",
            "judgment_dates": "25-09-2024",
            "temp_link": "supremecourt/2024/43583/43583_2024_1_301_56068_Judgement_25-Sep-2024.pdf (English)"
        },
        {
            "diary_no": "45336-2023",
            "Judgement_type": "J",
            "case_no": "MA-000267 - 2024",
            "pet": "ANANTDEEP SINGH",
            "res": "THE HIGH COURT OF PUNJAB AND HARYANA AT CHANDIGARH",
            "pet_adv": "ASHOK K. MAHAJAN",
            "res_adv": null,
            "bench": "HON&#39;BLE MR. JUSTICE VIKRAM NATH, HON&#39;BLE  MR. JUSTICE PRASANNA B. VARALE",
            "judgement_by": "HON&#39;BLE MR. JUSTICE VIKRAM NATH",
            "judgment_dates": "06-09-2024",
            "temp_link": "supremecourt/2023/45336/45336_2023_7_1502_55375_Judgement_06-Sep-2024.pdf (English)"
        },
        {
            "diary_no": "45531-2023",
            "Judgement_type": "J",
            "case_no": "Crl.A. No.-002030-002030 - 2024",
            "pet": "SANTOSH @ RAJESH @ GOPAL",
            "res": "THE STATE OF MADHYA PRADESH",
            "pet_adv": "SHWETA GARG",
            "res_adv": null,
            "bench": "HON&#39;BLE THE CHIEF JUSTICE, HON&#39;BLE MR. JUSTICE SANJAY KUMAR, HON&#39;BLE MR. JUSTICE R. MAHADEVAN",
            "judgement_by": "HON&#39;BLE THE CHIEF JUSTICE",
            "judgment_dates": "19-09-2024",
            "temp_link": "supremecourt/2023/45531/45531_2023_2_102_55759_Judgement_19-Sep-2024.pdf (English)"
        },
        {
            "diary_no": "47515-2023",
            "Judgement_type": "J",
            "case_no": "SLP(C) No.-025782 - 2023",
            "pet": "SIKHA GHOSH",
            "res": "INDIAN OIL CORPORATION LTD",
            "pet_adv": "SWARNENDU CHATTERJEE",
            "res_adv": null,
            "bench": "HON&#39;BLE MR. JUSTICE J.K. MAHESHWARI, HON&#39;BLE MR. JUSTICE RAJESH BINDAL",
            "judgement_by": "HON&#39;BLE MR. JUSTICE J.K. MAHESHWARI",
            "judgment_dates": "09-09-2024",
            "temp_link": "supremecourt/2023/47515/47515_2023_8_65_55468_Judgement_09-Sep-2024.pdf (English)"
        },
        {
            "diary_no": "49676-2023",
            "Judgement_type": "J",
            "case_no": "C.A. No.-002809-002810 - 2024",
            "pet": "DHARMENDRA SHARMA",
            "res": "AGRA DEVELOPMENT AUTHORITY VICE CHAIRMAN",
            "pet_adv": "VIKAS SINGH JANGRA",
            "res_adv": null,
            "bench": "HON&#39;BLE MR. JUSTICE VIKRAM NATH, HON&#39;BLE  MR. JUSTICE PRASANNA B. VARALE",
            "judgement_by": "HON&#39;BLE MR. JUSTICE VIKRAM NATH",
            "judgment_dates": "06-09-2024",
            "temp_link": "supremecourt/2023/49676/49676_2023_7_1503_55375_Judgement_06-Sep-2024.pdf (English)"
        },
        {
            "diary_no": "50777-2023",
            "Judgement_type": "J",
            "case_no": "Crl.A. No.-003327-003327 - 2024",
            "pet": "SHOYEB RAJA",
            "res": "STATE OF MADHYA PRADESH",
            "pet_adv": "NISHESH SHARMA",
            "res_adv": null,
            "bench": "HON&#39;BLE MR. JUSTICE C.T. RAVIKUMAR, HON&#39;BLE MR. JUSTICE SANJAY KAROL",
            "judgement_by": "HON&#39;BLE MR. JUSTICE C.T. RAVIKUMAR",
            "judgment_dates": "25-09-2024",
            "temp_link": "supremecourt/2023/50777/50777_2023_11_1502_56001_Judgement_25-Sep-2024.pdf (English)"
        },
        {
            "diary_no": "51276-2023",
            "Judgement_type": "J",
            "case_no": "Crl.A. No.-002501-002501 - 2024",
            "pet": "DHANRAJ ASWANI",
            "res": "AMAR S. MULCHANDANI",
            "pet_adv": "JURISTRUST LAW OFFICES",
            "res_adv": null,
            "bench": "HON&#39;BLE THE CHIEF JUSTICE, HON&#39;BLE MR. JUSTICE J.B. PARDIWALA, HON&#39;BLE MR. JUSTICE MANOJ MISRA",
            "judgement_by": "HON&#39;BLE THE CHIEF JUSTICE",
            "judgment_dates": "09-09-2024",
            "temp_link": "supremecourt/2023/51276/51276_2023_1_1501_55461_Judgement_09-Sep-2024.pdf (English)"
        }
    ],
    "error": 0
}