{
    "data": [
        {
            "diary_no": "1609-2024",
            "Judgement_type": "J",
            "case_no": "C.A. No.-013919-013919 - 2024",
            "pet": "BASUDEV DUTTA",
            "res": "THE STATE OF WEST BENGAL",
            "pet_adv": "SHEKHAR KUMAR",
            "res_adv": null,
            "bench": "HON&#39;BLE MR. JUSTICE J.B. PARDIWALA, HON&#39;BLE MR. JUSTICE R. MAHADEVAN",
            "judgement_by": "HON&#39;BLE MR. JUSTICE R. MAHADEVAN",
            "judgment_dates": "05-12-2024",
            "temp_link": "supremecourt/2024/1609/1609_2024_15_1501_57647_Judgement_05-Dec-2024.pdf (English)"
        },
        {
            "diary_no": "8716-2022",
            "Judgement_type": "J",
            "case_no": "C.A. No.-014029-014029 - 2024",
            "pet": "P. J. DHARMARAJ",
            "res": "CHURCH OF SOUTH INDIA",
            "pet_adv": "MANDEEP KALRA ",
            "res_adv": null,
            "bench": "HON&#39;BLE MR. JUSTICE VIKRAM NATH, HON&#39;BLE  MR. JUSTICE PRASANNA B. VARALE",
            "judgement_by": "HON&#39;BLE MR. JUSTICE VIKRAM NATH",
            "judgment_dates": "06-12-2024",
            "temp_link": "supremecourt/2022/8716/8716_2022_6_1502_57806_Judgement_06-Dec-2024.pdf (English)"
        },
        {
            "diary_no": "9208-2021",
            "Judgement_type": "J",
            "case_no": "Crl.A. No.-000573-000573 - 2023",
            "pet": "WADLA BHEEMARAIDU",
            "res": "THE STATE OF TELANGANA",
            "pet_adv": "ANIRUDDHA P. MAYEE",
            "res_adv": null,
            "bench": "HON&#39;BLE MR. JUSTICE DIPANKAR DATTA, HON&#39;BLE MR. JUSTICE SANDEEP MEHTA",
            "judgement_by": "HON&#39;BLE MR. JUSTICE DIPANKAR DATTA",
            "judgment_dates": "03-12-2024",
            "temp_link": "supremecourt/2021/9208/9208_2021_16_1501_57735_Judgement_03-Dec-2024.pdf (English)"
        },
        {
            "diary_no": "11481-2023",
            "Judgement_type": "J",
            "case_no": "C.A. No.-013708-013709 - 2024",
            "pet": "OACHIRA PARABRAHMA TEMPLE",
            "res": "G. VIJAYANATHAKURUP",
            "pet_adv": "RAMESHWAR PRASAD GOYAL",
            "res_adv": null,
            "bench": "HON&#39;BLE MR. JUSTICE J.B. PARDIWALA, HON&#39;BLE MR. JUSTICE R. MAHADEVAN",
            "judgement_by": "HON&#39;BLE MR. JUSTICE R. MAHADEVAN",
            "judgment_dates": "03-12-2024",
            "temp_link": "supremecourt/2023/11481/11481_2023_15_1501_57613_Judgement_03-Dec-2024.pdf (English)"
        },
        {
            "diary_no": "11789-2019",
            "Judgement_type": "J",
            "case_no": "Crl.A. No.-005097-005097 - 2024",
            "pet": "KUNHIMUHAMMED @ KUNHEETHU",
            "res": "THE STATE OF KERALA",
            "pet_adv": "RADHA SHYAM JENA",
            "res_adv": null,
            "bench": "HON&#39;BLE MR. JUSTICE VIKRAM NATH, HON&#39;BLE  MR. JUSTICE PRASANNA B. VARALE",
            "judgement_by": "HON&#39;BLE MR. JUSTICE VIKRAM NATH",
            "judgment_dates": "06-12-2024",
            "temp_link": "supremecourt/2019/11789/11789_2019_6_1501_57806_Judgement_06-Dec-2024.pdf (English)"
        },
        {
            "diary_no": "20250-2021",
            "Judgement_type": "J",
            "case_no": "C.A. No.-013730-013730 - 2024",
            "pet": "UNION OF INDIA",
            "res": "SAROJ DEVI",
            "pet_adv": "MUKESH KUMAR MARORIA",
            "res_adv": null,
            "bench": "HON&#39;BLE MR. JUSTICE ABHAY S. OKA, HON&#39;BLE MR. JUSTICE AUGUSTINE GEORGE MASIH",
            "judgement_by": "HON&#39;BLE MR. JUSTICE ABHAY S. OKA",
            "judgment_dates": "03-12-2024",
            "temp_link": "supremecourt/2021/20250/20250_2021_5_1501_57602_Judgement_03-Dec-2024.pdf (English)"
        },
        {
            "diary_no": "20371-2023",
            "Judgement_type": "J",
            "case_no": "C.A. No.-013958-013959 - 2024",
            "pet": "NUTAN BHARTI GRAM VIDYAPITH",
            "res": "GOVERNMENT OF GUJARAT",
            "pet_adv": "TARUNA SINGH GOHIL",
            "res_adv": null,
            "bench": "HON&#39;BLE MR. JUSTICE J.K. MAHESHWARI, HON&#39;BLE MR. JUSTICE RAJESH BINDAL",
            "judgement_by": "HON&#39;BLE MR. JUSTICE RAJESH BINDAL",
            "judgment_dates": "02-12-2024",
            "temp_link": "supremecourt/2023/20371/20371_2023_7_1502_57673_Judgement_02-Dec-2024.pdf (English)"
        },
        {
            "diary_no": "27483-2020",
            "Judgement_type": "J",
            "case_no": "W.P.(Crl.) No.-000416 - 2020",
            "pet": "KABIR SHANKAR BOSE",
            "res": "THE STATE OF WEST BENGAL",
            "pet_adv": null,
            "res_adv": null,
            "bench": "HON&#39;BLE MR. JUSTICE PANKAJ MITHAL, HON&#39;BLE MR. JUSTICE SANDEEP MEHTA",
            "judgement_by": "HON&#39;BLE MR. JUSTICE PANKAJ MITHAL",
            "judgment_dates": "04-12-2024",
            "temp_link": "supremecourt/2020/27483/27483_2020_17_1501_57642_Judgement_04-Dec-2024.pdf (English)"
        },
        {
            "diary_no": "28315-2023",
            "Judgement_type": "J",
            "case_no": "Crl.A. No.-004976-004976 - 2024",
            "pet": "IRFAN KHAN ",
            "res": " STATE (NCT OF DELHI)",
            "pet_adv": "ABISHEK JEBARAJ",
            "res_adv": null,
            "bench": "HON&#39;BLE MR. JUSTICE DIPANKAR DATTA, HON&#39;BLE MR. JUSTICE SANDEEP MEHTA",
            "judgement_by": "HON&#39;BLE MR. JUSTICE DIPANKAR DATTA",
            "judgment_dates": "03-12-2024",
            "temp_link": "supremecourt/2023/28315/28315_2023_16_1502_57735_Judgement_03-Dec-2024.pdf (English)"
        },
        {
            "diary_no": "30634-2012",
            "Judgement_type": "J",
            "case_no": "C.A. No.-009279-009279 - 2014",
            "pet": "BASTIRAM",
            "res": "RAJASTHAN STATE ROAD TRANSPORT CORPORATION",
            "pet_adv": "ABHISHEK GUPTA",
            "res_adv": "S. K. BHATTACHARYA",
            "bench": "HON&#39;BLE MR. JUSTICE J.K. MAHESHWARI, HON&#39;BLE MR. JUSTICE RAJESH BINDAL",
            "judgement_by": "HON&#39;BLE MR. JUSTICE RAJESH BINDAL",
            "judgment_dates": "02-12-2024",
            "temp_link": "supremecourt/2012/30634/30634_2012_7_1501_57673_Judgement_02-Dec-2024.pdf (English)"
        },
        {
            "diary_no": "43783-2024",
            "Judgement_type": "J",
            "case_no": "Crl.A. No.-004952-004952 - 2024",
            "pet": "HARE RAM YADAV",
            "res": "STATE OF BIHAR",
            "pet_adv": "SMARHAR SINGH",
            "res_adv": null,
            "bench": "HON&#39;BLE MR. JUSTICE B.R. GAVAI, HON&#39;BLE MR. JUSTICE K.V. VISWANATHAN",
            "judgement_by": "HON&#39;BLE MR. JUSTICE B.R. GAVAI",
            "judgment_dates": "03-12-2024",
            "temp_link": "supremecourt/2024/43783/43783_2024_2_16_57599_Judgement_03-Dec-2024.pdf (English)"
        },
        {
            "diary_no": "47292-2018",
            "Judgement_type": "J",
            "case_no": "Crl.A. No.-000771-000771 - 2024",
            "pet": "ASHOK",
            "res": "THE STATE OF UTTAR PRADESH",
            "pet_adv": "RAJIV NANDA",
            "res_adv": null,
            "bench": "HON&#39;BLE MR. JUSTICE ABHAY S. OKA, HON&#39;BLE MR. JUSTICE AUGUSTINE GEORGE MASIH",
            "judgement_by": "HON&#39;BLE MR. JUSTICE ABHAY S. OKA",
            "judgment_dates": "02-12-2024",
            "temp_link": "supremecourt/2018/47292/47292_2018_5_1501_57671_Judgement_02-Dec-2024.pdf (English)"
        }
    ],
    "error": 0
}